[
  {
    "date": "2026-02-12",
    "BTC": {
      "price": 65909.0,
      "top500": {
        "longCount": 48,
        "shortCount": 43,
        "longVal": 285205849,
        "shortVal": 246819014
      }
    },
    "ETH": {
      "price": 1930.5,
      "top500": {
        "longCount": 27,
        "shortCount": 62,
        "longVal": 305892279,
        "shortVal": 276019108
      }
    },
    "SOL": {
      "price": 77.51,
      "top500": {
        "longCount": 31,
        "shortCount": 28,
        "longVal": 57349208,
        "shortVal": 47786364
      }
    },
    "HYPE": {
      "price": 29.71,
      "top500": {
        "longCount": 32,
        "shortCount": 60,
        "longVal": 158384523,
        "shortVal": 228648002
      }
    }
  },
  {
    "date": "2026-02-13",
    "BTC": {
      "price": 67318.0,
      "top500": {
        "longCount": 48,
        "shortCount": 37,
        "longVal": 235505150,
        "shortVal": 202012297
      }
    },
    "ETH": {
      "price": 1970.3,
      "top500": {
        "longCount": 26,
        "shortCount": 60,
        "longVal": 316917733,
        "shortVal": 274932874
      }
    },
    "SOL": {
      "price": 80.38,
      "top500": {
        "longCount": 31,
        "shortCount": 30,
        "longVal": 61362169,
        "shortVal": 49647500
      }
    },
    "HYPE": {
      "price": 30.88,
      "top500": {
        "longCount": 30,
        "shortCount": 62,
        "longVal": 156835991,
        "shortVal": 231913592
      }
    }
  }
]