{"lastUpdated": "2026-02-09T15:15:20.906903Z", "tradersCount": 30541, "coins": ["ETH", "HYPE", "PAXG", "PUMP", "WLFI", "ZEC", "LIT", "BTC", "SOL", "MON", "XRP", "MET", "CELO", "CC"], "data": {"ETH": {"currentPrice": 2056.0, "longLiquidations": [], "shortLiquidations": [{"price": 2150, "10x": 313883.47617, "25x": 0, "50x": 0, "100x": 0}, {"price": 2200, "10x": 3950834.6832, "25x": 0, "50x": 0, "100x": 0}, {"price": 2300, "10x": 0, "25x": 6260063.96573, "50x": 0, "100x": 0}, {"price": 2350, "10x": 0, "25x": 5040422.84018, "50x": 0, "100x": 0}, {"price": 2500, "10x": 733629.73502, "25x": 185103.0, "50x": 0, "100x": 0}, {"price": 2550, "10x": 19310588.75659, "25x": 511452.97476, "50x": 0, "100x": 0}, {"price": 2600, "10x": 0, "25x": 4597340.7992, "50x": 0, "100x": 0}, {"price": 2650, "10x": 1542525.0, "25x": 0, "50x": 0, "100x": 0}, {"price": 2700, "10x": 0, "25x": 17492233.5, "50x": 0, "100x": 0}, {"price": 2750, "10x": 1295424.8352, "25x": 17335663.0991, "50x": 0, "100x": 0}, {"price": 2800, "10x": 1908565.97683, "25x": 0, "50x": 0, "100x": 0}, {"price": 2850, "10x": 626445.11125, "25x": 0, "50x": 0, "100x": 0}, {"price": 2900, "10x": 0, "25x": 4809875.23517, "50x": 0, "100x": 0}, {"price": 2950, "10x": 614416.5013, "25x": 0, "50x": 0, "100x": 0}, {"price": 3000, "10x": 1085855.332, "25x": 0, "50x": 0, "100x": 0}]}, "HYPE": {"currentPrice": 31.981, "longLiquidations": [{"price": 18, "10x": 4178122.5000099996, "25x": 0, "50x": 0, "100x": 0}, {"price": 25, "10x": 2720595.0, "25x": 0, "50x": 0, "100x": 0}], "shortLiquidations": [{"price": 34, "10x": 2265655.09492, "25x": 0, "50x": 0, "100x": 0}, {"price": 38, "10x": 1586959.04864, "25x": 0, "50x": 0, "100x": 0}, {"price": 40, "10x": 479878.39044, "25x": 0, "50x": 0, "100x": 0}, {"price": 42, "10x": 836510.62668, "25x": 0, "50x": 0, "100x": 0}, {"price": 43, "10x": 13852107.96312, "25x": 0, "50x": 0, "100x": 0}, {"price": 45, "10x": 33074700.70845, "25x": 0, "50x": 0, "100x": 0}, {"price": 47, "10x": 7311354.17628, "25x": 0, "50x": 0, "100x": 0}]}, "PAXG": {"currentPrice": 5039.9, "longLiquidations": [{"price": 4000, "10x": 842983.7538, "25x": 0, "50x": 0, "100x": 0}], "shortLiquidations": [{"price": 7400, "10x": 1416405.5512, "25x": 0, "50x": 0, "100x": 0}]}, "PUMP": {"currentPrice": 0.002037, "longLiquidations": [{"price": 0.0, "10x": 586579.660626, "25x": 0, "50x": 0, "100x": 0}], "shortLiquidations": []}, "WLFI": {"currentPrice": 0.10808, "longLiquidations": [{"price": 0.07, "10x": 14058.96128, "25x": 0, "50x": 0, "100x": 0}], "shortLiquidations": []}, "ZEC": {"currentPrice": 236.55, "longLiquidations": [{"price": 140, "10x": 558569.394, "25x": 0, "50x": 0, "100x": 0}], "shortLiquidations": []}, "LIT": {"currentPrice": 1.5331, "longLiquidations": [{"price": 1.2, "10x": 29617.9589, "25x": 0, "50x": 0, "100x": 0}], "shortLiquidations": [{"price": 2.2, "10x": 2819110.172, "25x": 0, "50x": 0, "100x": 0}]}, "BTC": {"currentPrice": 69436.0, "longLiquidations": [{"price": 42000, "10x": 1981459.41684, "25x": 0, "50x": 0, "100x": 0}, {"price": 65000, "10x": 203343.5365, "25x": 0, "50x": 0, "100x": 0}], "shortLiquidations": [{"price": 72000, "10x": 6443361.85656, "25x": 0, "50x": 0, "100x": 0}, {"price": 73000, "10x": 0, "25x": 5174228.54772, "50x": 0, "100x": 0}, {"price": 74000, "10x": 11217544.01744, "25x": 0, "50x": 0, "100x": 0}, {"price": 75000, "10x": 2556788.5539, "25x": 0, "50x": 0, "100x": 0}, {"price": 76000, "10x": 4166520.0, "25x": 0, "50x": 0, "100x": 0}, {"price": 77000, "10x": 14606781.939, "25x": 9473935.59542, "50x": 0, "100x": 0}, {"price": 78000, "10x": 1214407.63185, "25x": 1003340.39893, "50x": 0, "100x": 0}, {"price": 79000, "10x": 3053267.30212, "25x": 0, "50x": 0, "100x": 0}, {"price": 80000, "10x": 0, "25x": 2847737.0, "50x": 0, "100x": 0}, {"price": 82000, "10x": 6951488.89356, "25x": 0, "50x": 0, "100x": 0}, {"price": 83000, "10x": 1202195.50488, "25x": 416772.0, "50x": 0, "100x": 0}, {"price": 85000, "10x": 24918612.4173, "25x": 0, "50x": 0, "100x": 0}, {"price": 87000, "10x": 2084428.70886, "25x": 0, "50x": 0, "100x": 0}, {"price": 88000, "10x": 10416300.0, "25x": 0, "50x": 0, "100x": 0}, {"price": 89000, "10x": 2597820.0720699998, "25x": 24309950.0, "50x": 0, "100x": 0}, {"price": 92000, "10x": 0, "25x": 23577471.62992, "50x": 0, "100x": 0}, {"price": 93000, "10x": 1389240.0, "25x": 903275.14804, "50x": 0, "100x": 0}, {"price": 96000, "10x": 833484.0, "25x": 0, "50x": 0, "100x": 0}, {"price": 98000, "10x": 667321.434, "25x": 2251912.4596, "50x": 0, "100x": 0}, {"price": 99000, "10x": 4167720.0, "25x": 0, "50x": 0, "100x": 0}, {"price": 100000, "10x": 1442378.39316, "25x": 0, "50x": 0, "100x": 0}, {"price": 101000, "10x": 5961030.00562, "25x": 0, "50x": 0, "100x": 0}, {"price": 102000, "10x": 4166520.0, "25x": 2387415.96, "50x": 0, "100x": 0}, {"price": 103000, "10x": 0, "25x": 3581605.94614, "50x": 0, "100x": 0}]}, "SOL": {"currentPrice": 85.034, "longLiquidations": [{"price": 55, "10x": 681389.982, "25x": 0, "50x": 0, "100x": 0}], "shortLiquidations": [{"price": 95, "10x": 6815261.265419999, "25x": 0, "50x": 0, "100x": 0}, {"price": 100, "10x": 6890171.840240001, "25x": 0, "50x": 0, "100x": 0}, {"price": 105, "10x": 6508117.506949999, "25x": 0, "50x": 0, "100x": 0}, {"price": 110, "10x": 4497502.15982, "25x": 0, "50x": 0, "100x": 0}, {"price": 115, "10x": 15319040.1525, "25x": 0, "50x": 0, "100x": 0}, {"price": 120, "10x": 7322175.262990001, "25x": 0, "50x": 0, "100x": 0}]}, "MON": {"currentPrice": 0.017606, "longLiquidations": [{"price": 0.01, "10x": 31007.0112, "25x": 0, "50x": 0, "100x": 0}], "shortLiquidations": [{"price": 0.02, "10x": 188.1968, "25x": 0, "50x": 0, "100x": 0}]}, "XRP": {"currentPrice": 1.4311, "longLiquidations": [{"price": 0.8, "10x": 1295701.6828, "25x": 0, "50x": 0, "100x": 0}], "shortLiquidations": [{"price": 1.7, "10x": 330809.2125, "25x": 0, "50x": 0, "100x": 0}, {"price": 1.8, "10x": 1634220.7249999999, "25x": 0, "50x": 0, "100x": 0}]}, "MET": {"currentPrice": 0.21031, "longLiquidations": [{"price": 0.16, "10x": 6053.8392, "25x": 0, "50x": 0, "100x": 0}], "shortLiquidations": []}, "CELO": {"currentPrice": 0.082727, "longLiquidations": [], "shortLiquidations": [{"price": 0.12, "10x": 106520.443378, "25x": 0, "50x": 0, "100x": 0}]}, "CC": {"currentPrice": 0.16518, "longLiquidations": [{"price": 0.13, "10x": 164.85962, "25x": 0, "50x": 0, "100x": 0}], "shortLiquidations": []}}}